snake_query_sdk/__init__.py
snake_query_sdk/client.py
snake_query_sdk/exceptions.py
snake_query_sdk/schema_builder.py
snake_query_sdk-1.0.3.dist-info/METADATA
snake_query_sdk-1.0.3.dist-info/WHEEL
snake_query_sdk-1.0.3.dist-info/top_level.txt
snake_query_sdk-1.0.3.dist-info/RECORD
