Metadata-Version: 2.4
Name: snake-query-sdk
Version: 1.0.3
Summary: Python SDK for Snake Query API - Natural language data querying with AI
Home-page: http://snakequery.com/
Author: Snake Query
Author-email: info@snakequery.com
Project-URL: Bug Reports, https://github.com/snakequery/snake-query-python-sdk/issues
Project-URL: Source, https://github.com/snakequery/snake-query-python-sdk/
Project-URL: Documentation, https://docs.snakequery.com/python-sdk
Keywords: snake-query,api,natural-language,data-query,ai,sdk
Classifier: Programming Language :: Python :: 3
Classifier: License :: OSI Approved :: MIT License
Classifier: Operating System :: OS Independent
Requires-Python: >=3.7
Requires-Dist: requests>=2.25.0
Dynamic: author
Dynamic: author-email
Dynamic: classifier
Dynamic: description
Dynamic: description-content-type
Dynamic: home-page
Dynamic: keywords
Dynamic: project-url
Dynamic: requires-dist
Dynamic: requires-python
Dynamic: summary
